{"name":null,"assets":"aoy4:pathy35:assets%2FbackGround%2Fdesert_BG.pngy4:sizei40660y4:typey5:IMAGEy2:idR1goR0y40:assets%2FbackGround%2FgameOverScreen.pngR2i100976R3R4R5R6goR0y36:assets%2FbackGround%2FgameScreen.pngR2i448276R3R4R5R7goR0y37:assets%2FbackGround%2FrulesScreen.pngR2i81718R3R4R5R8goR0y37:assets%2FbackGround%2FstartScreen.pngR2i11036R3R4R5R9goR0y28:assets%2FtileMap%2Fgrass.pngR2i6766R3R4R5R10goR0y33:assets%2FtileMap%2FPixelAtlas.pngR2i5091R3R4R5R11gh","rootPath":"../","version":2,"libraryArgs":[],"libraryType":null}